flask_argon2.py
Flask_Argon2-0.3.0.0.dist-info/LICENSE
Flask_Argon2-0.3.0.0.dist-info/METADATA
Flask_Argon2-0.3.0.0.dist-info/WHEEL
Flask_Argon2-0.3.0.0.dist-info/top_level.txt
Flask_Argon2-0.3.0.0.dist-info/RECORD
