Metadata-Version: 2.1
Name: Flask-Argon2
Version: 0.3.0.0
Summary: Flask-Argon2 provides convenient wrappers for Argon2 password hashing
Home-page: https://github.com/red-coracle/flask-argon2
Author: DominusTemporis
Author-email: python@dominustemporis.com
License: MIT
Platform: any
Classifier: Development Status :: 4 - Beta
Classifier: Environment :: Web Environment
Classifier: Intended Audience :: Developers
Classifier: License :: OSI Approved :: MIT License
Classifier: Operating System :: OS Independent
Classifier: Programming Language :: Python
Classifier: Topic :: Internet :: WWW/HTTP :: Dynamic Content
Classifier: Topic :: Software Development :: Libraries :: Python Modules
License-File: LICENSE
